main.py
artipull-0.0.1.dist-info/METADATA
artipull-0.0.1.dist-info/WHEEL
artipull-0.0.1.dist-info/top_level.txt
artipull-0.0.1.dist-info/RECORD
