Metadata-Version: 2.1
Name: artipull
Version: 0.0.1
Summary: A package for pulling news articles directly from a website given the URL
Author-email: Nicholas Kraftor <kraftmatic@pm.me>
Project-URL: Homepage, https://github.com/kraftmatic/ArtiPull
Project-URL: Bug Tracker, https://github.com/kraftmatic/ArtiPull/issues
Classifier: Programming Language :: Python :: 3
Classifier: License :: OSI Approved :: MIT License
Classifier: Operating System :: OS Independent
Requires-Python: >=3.7
